<filename>SURF_ZH_20240701200026_27643.xml</filename><mtime>20240701200026</mtime>
<filename>SURF_ZH_20240701200158_27924.xml</filename><mtime>20240701200158</mtime>
<filename>SURF_ZH_20240701200258_28145.xml</filename><mtime>20240701200258</mtime>
<filename>SURF_ZH_20240701200358_28229.xml</filename><mtime>20240701200358</mtime>
<filename>SURF_ZH_20240701200458_28314.xml</filename><mtime>20240701200458</mtime>
<filename>SURF_ZH_20240701200558_28398.xml</filename><mtime>20240701200558</mtime>
<filename>SURF_ZH_20240701200658_28487.xml</filename><mtime>20240701200658</mtime>
<filename>SURF_ZH_20240701200758_28580.xml</filename><mtime>20240701200758</mtime>
<filename>SURF_ZH_20240701200858_28672.xml</filename><mtime>20240701200858</mtime>
<filename>SURF_ZH_20240701200958_28754.xml</filename><mtime>20240701200958</mtime>
<filename>SURF_ZH_20240701201058_28842.xml</filename><mtime>20240701201058</mtime>
<filename>SURF_ZH_20240701201158_28928.xml</filename><mtime>20240701201158</mtime>
<filename>SURF_ZH_20240701201258_29059.xml</filename><mtime>20240701201258</mtime>
<filename>SURF_ZH_20240701201358_29140.xml</filename><mtime>20240701201358</mtime>
<filename>SURF_ZH_20240701201458_29225.xml</filename><mtime>20240701201458</mtime>
<filename>SURF_ZH_20240701201558_29307.xml</filename><mtime>20240701201558</mtime>
<filename>SURF_ZH_20240701201658_29397.xml</filename><mtime>20240701201658</mtime>
<filename>SURF_ZH_20240701201758_29484.xml</filename><mtime>20240701201758</mtime>
<filename>SURF_ZH_20240701201858_29571.xml</filename><mtime>20240701201858</mtime>
<filename>SURF_ZH_20240701201958_29652.xml</filename><mtime>20240701201958</mtime>
<filename>SURF_ZH_20240701202058_29740.xml</filename><mtime>20240701202058</mtime>
<filename>SURF_ZH_20240701202158_29832.xml</filename><mtime>20240701202158</mtime>
